[
  {
    "name": "Cartão de Visita 4x4",
    "format": "85x55mm",
    "widthMm": 85,
    "heightMm": 55,
    "printing": {
      "technology": "DIGITAL",
      "colors": "4x4",
      "unitPrice": "0.3040",
      "sides": 2,
      "yield": null
    },
    "finishes": [
      {
        "name": "Plastificação (face)",
        "active": true,
        "baseCost": "0.1000"
      }
    ],
    "suggested": [
      50,
      100,
      250,
      500,
      750,
      1000
    ],
    "totals": {
      "qty": 1000,
      "total": "143.20",
      "unit": "0.1432"
    }
  },
  {
    "name": "Cartão de Visita Plastificado F/V",
    "format": "85x55mm",
    "widthMm": 85,
    "heightMm": 55,
    "printing": {
      "technology": "DIGITAL",
      "colors": "4x4",
      "unitPrice": "0.2150",
      "sides": 2,
      "yield": null
    },
    "finishes": [
      {
        "name": "Plastificação (face)",
        "active": true,
        "baseCost": "0.0500"
      }
    ],
    "suggested": [
      100,
      250,
      500,
      750,
      1000
    ],
    "totals": {
      "qty": 1000,
      "total": "191.20",
      "unit": "0.1912"
    }
  },
  {
    "name": "Cartão de Visita Plastificado + Foil 1F",
    "format": "85x55mm",
    "widthMm": 85,
    "heightMm": 55,
    "printing": {
      "technology": "DIGITAL",
      "colors": "4x4",
      "unitPrice": "0.2150",
      "sides": 2,
      "yield": null
    },
    "finishes": [
      {
        "name": "Plastificação (face)",
        "active": true,
        "baseCost": "0.0500"
      },
      {
        "name": "Foil 1F",
        "baseCost": "0.0425"
      }
    ],
    "suggested": [
      100,
      200,
      500,
      750,
      1000
    ],
    "totals": {
      "qty": 200,
      "total": "80.25",
      "unit": "0.4012"
    }
  },
  {
    "name": "Cartão de Visita Plastificado + Foil 2F",
    "format": "85x55mm",
    "widthMm": 85,
    "heightMm": 55,
    "printing": {
      "technology": "DIGITAL",
      "colors": "4x4",
      "unitPrice": "0.2150",
      "sides": 2,
      "yield": null
    },
    "finishes": [
      {
        "name": "Plastificação (face)",
        "active": true,
        "baseCost": "0.0500"
      },
      {
        "name": "Foil 2F",
        "baseCost": "0.0850"
      }
    ],
    "suggested": [
      100,
      250,
      500,
      750,
      1000
    ],
    "totals": {
      "qty": 1000,
      "total": "271.10",
      "unit": "0.2711"
    }
  }
]